tbcml/__init__.py
tbcml/__main__.py
tbcml/py.typed
tbcml/core/__init__.py
tbcml/core/country_code.py
tbcml/core/crypto.py
tbcml/core/game_version.py
tbcml/core/langs.py
tbcml/core/locale_handler.py
tbcml/core/log.py
tbcml/core/request.py
tbcml/core/server_handler.py
tbcml/core/anim/__init__.py
tbcml/core/anim/model.py
tbcml/core/anim/model_part.py
tbcml/core/anim/rect.py
tbcml/core/anim/texture.py
tbcml/core/anim/unit_animation.py
tbcml/core/game_data/__init__.py
tbcml/core/game_data/bcu.py
tbcml/core/game_data/localizable.py
tbcml/core/game_data/pack.py
tbcml/core/game_data/battle/__init__.py
tbcml/core/game_data/battle/base_ability.py
tbcml/core/game_data/battle/battle_shake_setting.py
tbcml/core/game_data/battle/bg.py
tbcml/core/game_data/battle/chara_group.py
tbcml/core/game_data/cat_base/__init__.py
tbcml/core/game_data/cat_base/adjust_track.py
tbcml/core/game_data/cat_base/cats.py
tbcml/core/game_data/cat_base/enemies.py
tbcml/core/game_data/cat_base/gatya.py
tbcml/core/game_data/cat_base/gatya_item.py
tbcml/core/game_data/cat_base/item_shop.py
tbcml/core/game_data/cat_base/matatabi.py
tbcml/core/game_data/cat_base/scheme_item.py
tbcml/core/game_data/cat_base/unit.py
tbcml/core/game_data/cat_base/user_rank_reward.py
tbcml/core/game_data/gamototo/__init__.py
tbcml/core/game_data/gamototo/cannon.py
tbcml/core/game_data/gamototo/engineers.py
tbcml/core/game_data/gamototo/item_pack.py
tbcml/core/game_data/gamototo/ototo_anim.py
tbcml/core/game_data/map/__init__.py
tbcml/core/game_data/map/map.py
tbcml/core/io/__init__.py
tbcml/core/io/apk.py
tbcml/core/io/asset_loader.py
tbcml/core/io/audio.py
tbcml/core/io/bc_csv.py
tbcml/core/io/bc_image.py
tbcml/core/io/command.py
tbcml/core/io/config.py
tbcml/core/io/data.py
tbcml/core/io/file_handler.py
tbcml/core/io/json_file.py
tbcml/core/io/lib.py
tbcml/core/io/path.py
tbcml/core/io/temp_file.py
tbcml/core/io/xml_parse.py
tbcml/core/io/yaml.py
tbcml/core/io/zip.py
tbcml/core/mods/__init__.py
tbcml/core/mods/bc_mod.py
tbcml-1.1.0.dist-info/LICENSE
tbcml-1.1.0.dist-info/METADATA
tbcml-1.1.0.dist-info/WHEEL
tbcml-1.1.0.dist-info/top_level.txt
tbcml-1.1.0.dist-info/RECORD
