Metadata-Version: 2.1
Name: tbcml
Version: 1.1.0
Summary: A mod loader for The Battle Cats
Home-page: https://github.com/fieryhenry/TBCModLoader
Author: fieryhenry
Classifier: Programming Language :: Python :: 3
Classifier: License :: OSI Approved :: MIT License
Classifier: Operating System :: OS Independent
Requires-Python: >=3.9
License-File: LICENSE
Requires-Dist: beautifulsoup4
Requires-Dist: cloudscraper
Requires-Dist: cryptography
Requires-Dist: Pillow
Requires-Dist: pycryptodomex
Requires-Dist: PyYAML
Requires-Dist: requests
Requires-Dist: ffmpeg-python
Provides-Extra: scripting
Requires-Dist: androguard ; extra == 'scripting'
Requires-Dist: lief ; extra == 'scripting'
Provides-Extra: testing
Requires-Dist: pytest ; extra == 'testing'
Requires-Dist: pytest-cov ; extra == 'testing'
Provides-Extra: ui
Requires-Dist: PyQt5 ; extra == 'ui'
Requires-Dist: qtawesome ; extra == 'ui'
Requires-Dist: moviepy ; extra == 'ui'
